setup.py
sphinxcontrib/__init__.py
sphinxcontrib/yuml.py
sphinxcontrib_yuml.egg-info/PKG-INFO
sphinxcontrib_yuml.egg-info/SOURCES.txt
sphinxcontrib_yuml.egg-info/dependency_links.txt
sphinxcontrib_yuml.egg-info/top_level.txt