Metadata-Version: 1.1
Name: sphinxcontrib-yuml
Version: 0.1
Summary: Sphinx extension for embedding yuml diagram in documentations
Home-page: https://github.com/njouanin/sphinxcontrib-yuml
Author: UNKNOWN
Author-email: UNKNOWN
License: GPLv3
Platform: any
Classifier: Development Status :: 4 - Beta
Classifier: Environment :: Console
Classifier: Environment :: Web Environment
Classifier: Intended Audience :: Developers
Classifier: License :: OSI Approved :: BSD License
Classifier: Operating System :: OS Independent
Classifier: Programming Language :: Python
Classifier: Topic :: Documentation
Classifier: Topic :: Utilities
